drunken_child_in_the_fog/__init__.py
drunken_child_in_the_fog/core.py
drunken_child_in_the_fog-0.3.1.dist-info/DESCRIPTION.rst
drunken_child_in_the_fog-0.3.1.dist-info/METADATA
drunken_child_in_the_fog-0.3.1.dist-info/RECORD
drunken_child_in_the_fog-0.3.1.dist-info/WHEEL
drunken_child_in_the_fog-0.3.1.dist-info/entry_points.txt
drunken_child_in_the_fog-0.3.1.dist-info/metadata.json
drunken_child_in_the_fog-0.3.1.dist-info/top_level.txt
