Metadata-Version: 2.0
Name: drunken-child-in-the-fog
Version: 0.3.1
Summary: PDF parser API inspired by Django QuerySet, using PDFMiner.six
Home-page: https://github.com/mpasternak/drunken_child_in_the_fog
Author: Michał Pasternak
Author-email: michal.dtz@gmail.com
License: MIT license
Keywords: drunken_child_in_the_fog
Platform: UNKNOWN
Classifier: Development Status :: 2 - Pre-Alpha
Classifier: Intended Audience :: Developers
Classifier: License :: OSI Approved :: MIT License
Classifier: Natural Language :: English
Classifier: Programming Language :: Python :: 2
Classifier: Programming Language :: Python :: 2.6
Classifier: Programming Language :: Python :: 2.7
Classifier: Programming Language :: Python :: 3
Classifier: Programming Language :: Python :: 3.3
Classifier: Programming Language :: Python :: 3.4
Classifier: Programming Language :: Python :: 3.5
Requires-Dist: pdfminer.six (==20170419)
